LICENSE
MANIFEST.in
README.md
requirements.txt
setup.py
robogame_engine/__init__.py
robogame_engine/commands.py
robogame_engine/constants.py
robogame_engine/events.py
robogame_engine/exceptions.py
robogame_engine/geometry.py
robogame_engine/objects.py
robogame_engine/scene.py
robogame_engine/states.py
robogame_engine/theme.py
robogame_engine/user_interface.py
robogame_engine/utils.py
robogame_engine.egg-info/PKG-INFO
robogame_engine.egg-info/SOURCES.txt
robogame_engine.egg-info/dependency_links.txt
robogame_engine.egg-info/requires.txt
robogame_engine.egg-info/top_level.txt
robogame_engine/fonts/COPYING
robogame_engine/fonts/TerminusTTF-4.39.ttf
robogame_engine/fonts/TerminusTTF-Bold-4.39.ttf
robogame_engine/fonts/TerminusTTF-Italic-4.39.ttf
tests/__init__.py
tests/default_theme.py
tests/test_moving.py
tests/test_turning.py