Metadata-Version: 2.1
Name: robogame-engine
Version: 1.3.0
Summary: The package allows you to create RoboGames.
Home-page: https://github.com/suguby/robogame_engine
Author: Shandrinov Vadim
Author-email: suguby@gmail.com
License: BSD License
Platform: UNKNOWN
Classifier: Development Status :: 4 - Beta
Classifier: License :: OSI Approved :: BSD License
Classifier: Programming Language :: Python
Classifier: Programming Language :: Python :: 3.6
Classifier: Programming Language :: Python :: 3.7
Classifier: Programming Language :: Python :: 3.8
